po_meta_magic/__init__.py
po_meta_magic/core.py
po_meta_magic-0.1.7.dist-info/METADATA
po_meta_magic-0.1.7.dist-info/WHEEL
po_meta_magic-0.1.7.dist-info/top_level.txt
po_meta_magic-0.1.7.dist-info/RECORD
