Metadata-Version: 2.1
Name: po_meta_magic
Version: 0.1.7
Summary: A Python package for extracting and processing text from images.
Home-page: https://github.com/yourusername/po_meta_magic
Author: Muhammad Abuzar
Author-email: abuzar9658@gmail.com
Classifier: Programming Language :: Python :: 3
Classifier: License :: OSI Approved :: MIT License
Classifier: Operating System :: OS Independent
Requires-Python: >=3.6
Requires-Dist: pillow
Requires-Dist: fuzzywuzzy
Requires-Dist: python-dateutil
Requires-Dist: pytesseract
